<?xml version='1.0' encoding='UTF-8'?>
<parameters model_name="general_driver_model">



	
	
	
	

	<param name="min_response_distance" value="5.4124" />
	
	
		
	
	 
	 
	
	
	

	
									
	<param name="CF_parameters_1" value="0.046198 0.9 0.1845 0.65311 0.58004 0.0" />
	<param name="CF_parameters_2" value="-0.089623 0 0.44074 0.55045 0.64428 0.0" />
	
	
															
	
	<param name="Car_following_acceleration_add_on" value="  -1.7945 -1.1307 -0.7358 -0.4203 -0.1370 0.1370 0.4203 0.7358 1.1307 1.7945" />
	
	<param name="Car_following_deceleration_add_on" value="  -0.8092 -0.5099 -0.3318 -0.1895 -0.0618 0.0618 0.1895 0.3318 0.5099 0.8092" />

	


	
	
	
	

	<param name="FF_Acc_Params_b0" value="10.0" />
	<param name="FF_Acc_Params_b2" value="0.05" />
	<param name="FF_Acc_Params_stddev" value="1.15" />



	
	
	
	
	
	
	
	<param name="speed_factor" value="1.43" />
	
	
										
	<param name="speed_limit_add_on" value="-0.3125 -0.1969 -0.1281 -0.0732 -0.0238 0.0238 0.0732 0.1281 0.1969 0.3125" />

	
	

	
		
	
	
											
	<param name="target_gap_acc_parm" value="0.68198 0.6 0.56531 0.071363 0.14661 0.51282 -0.72518 -0.42112 0.052345 0.18688 0.8 0.068675 0.41211" />
	
	 
	
	
	<param name="max_acc_car1" value="6.6 4.95 4.9969 4.05 3.6" />
	
	<param name="normal_deceleration_car1" value="-2.75 -2.025 -2.2 -1.925 -1.65" />
	
	<param name="max_deceleration_car1" value="-8.6898 -7.65 -7.2 -8.25 -6.5216" />

	
												
	<param name="max_acceleration_scale" value="0.75 0.80 0.85 0.90 0.95 1.00 1.05 1.10 1.15 1.20" />
	<param name="normal_deceleration_scale" value="0.75 0.80 0.85 0.90 0.95 1.00 1.05 1.10 1.15 1.20" />
	<param name="max_deceleration_scale" value="0.75 0.80 0.85 0.90 0.95 1.00 1.05 1.10 1.15 1.20" />
	
	
		
	<param name="speed_scaler" value="5 10 5" />
	
	<param name="acceleration_grade_factor" value="1" />
	
	<param name="tmp_all_grades" value="0" />

	


	
	
  <param name="hbuffer_lower" value="1.1" />
  
	
	
											
	
	
	
	
	
	<param name="hbuffer_Upper" value="2.0332 2.3196 2.4914 2.606 2.7492 2.8637 2.9782 3.1214 3.2933 3.5796" />


	<param name="yellow_stop_headway" value="0.9" />	
	<param name="min_speed_yellow" value="2.4587" />	
	<param name="driver_signal_perception_distance" value="135" /> 


														
	
	
	

	
	

	<param name="dec_update_step_size" value="0.36 0.10 0.25 1.05 0.0" />
	<param name="acc_update_step_size" value="0.45 0.10 0.30 1.55 0.0" />
	<param name="uniform_speed_update_step_size" value="0.45 0.10 0.30 1.55 0.0" />
	<param name="stopped_vehicle_update_step_size" value="0.36 0.10 0.25 1.05 0.0" />



	<param name="visibility_distance" value="10" />



                                   
	<param name="MLC_PARAMETERS" value="405.785 917.392 2" />
	
	


	
	
	
	
	
	
	<param name="lane_utility_model" value="6 0.28917 -0.88563 0 0.051701 -0.50221 0.0054472 -0.15 -0.0052747 -1.75 6.9504 20.9832 -2.0463 -6.5 -1.5784 -0.92842 -0.69237 -0.37049" />



									
	<param name="LC_GAP_MODELS_0" value="1.00, 0.0, 0.000, 0.508, 0.000, 0.000, -0.420, 0.000, 0.488" />
	<param name="LC_GAP_MODELS_1" value="1.00, 0.0, 0.000, 2.020, 0.000, 0.000, 0.153, 0.188, 0.526" />
	<param name="LC_GAP_MODELS_2" value="1.00, 0.0, 0.000, 0.384, 0.000, 0.000, 0.000, 0.000, 0.859" />
	<param name="LC_GAP_MODELS_3" value="1.00, 0.0, 0.000, 0.587, 0.000, 0.000, 0.048, 0.356, 1.073" />
	<param name="LC_GAP_MODELS_4" value="0.60, 0.0, 0.000, 0.384, 0.000, 0.000, 0.000, 0.000, 0.859" />
	<param name="LC_GAP_MODELS_5" value="0.60, 0.0, 0.000, 0.587, 0.000, 0.000, 0.048, 0.356, 1.073" />
	<param name="LC_GAP_MODELS_6" value="0.20, 0.0, 0.000, 0.384, 0.000, 0.000, 0.000, 0.000, 0.859" />
	<param name="LC_GAP_MODELS_7" value="0.20, 0.0, 0.000, 0.587, 0.000, 0.000, 0.048, 0.356, 1.073" />

	<param name="critical_gaps_param" value="0.57056 -0.35 -3.6473 0.87417 0.57925 0 0.17938 0.52651 0.070359" />

	
	<param name="Target_Gap_Model" value="-0.9207 0.8217 0.7344 -1.0962 -2.1537 -1.8282" />


									
	<param name="GAP_PARAM_0" value="-1.23, -0.482, 0.224, -0.0179, 2.10, 0.239" />   #back
	<param name="GAP_PARAM_1" value="0.00, 0.00, 0.224, -0.0179, 2.10, 0.000" />   #adj
	<param name="GAP_PARAM_2" value="-0.772, -0.482, 0.224, -0.0179, 2.10, 0.675" />   #fwd



	<param name="nosing_param" value="1.0157 0.45 0.58253 0.09 0.45 1.0157 27 99.7925 540.7268 44" />
	



	<param name="kazi_nosing_param" value="-3.159 0.313 -0.027 2.050 0.028 0.6" />

	
	<param name="CF_CRITICAL_TIMER_RATIO" value="0.45" />

	
	<param name="LC_Yielding_Model" value="0.80 1.00" />
	
	
	
	<param name="MLC_Yielding_Probabilities" value="0.13 0.71 0.13 0.03" />
	

	
	
	<param name="intersection_attentiveness_factor_min" value="0.27" />
	<param name="intersection_attentivneess_factor_max" value="0.66" />
	
	
	<param name="minimum_gap" value="1.375" />
	
	
										
	<param name="critical_gap_addon" value="0.9 0.45 0.5" />
	
	
	<param name="impatience_factor" value="0.19997" />
	
	
	
	
	<param name="tailgate_separation_time" value="1" />
	
	
	<param name="conflict_separation_time" value="2.46" />	
	
	
	
	<param name="min_speed" value="0.1" />  
	
	
	<param name="LC_Discretionary_Lane_Change_Model_MinTimeInLaneSameDir" value="6.3" /> 
	<param name="LC_Discretionary_Lane_Change_Model_MinTimeInLaneDiffDir" value="16.5" /> 

	
	<param name="check_stop_point_distance" value="200" /> 

	
	<param name="density" value="0.0" /> 
	
</parameters>