<?xml version='1.0' encoding='UTF-8'?>
<parameters model_name="general_driver_model">



	
	
	
	

	<param name="min_response_distance" value="5.5631" />
	
	
		
	
	 
	 
	
	
	

	
									
	<param name="CF_parameters_1" value="0.036898 0.40456 0.2255 0.54818 0.45179 0.0" />
	<param name="CF_parameters_2" value="-0.083196 0 0.66676 0.85846 0.91329 0.0" />
	
	
															
	
	<param name="Car_following_acceleration_add_on" value="  -1.7945 -1.1307 -0.7358 -0.4203 -0.1370 0.1370 0.4203 0.7358 1.1307 1.7945" />
	
	<param name="Car_following_deceleration_add_on" value="  -0.8092 -0.5099 -0.3318 -0.1895 -0.0618 0.0618 0.1895 0.3318 0.5099 0.8092" />

	


	
	
	
	

	<param name="FF_Acc_Params_b0" value="10.0" />
	<param name="FF_Acc_Params_b2" value="0.069792" />
	<param name="FF_Acc_Params_stddev" value="1.15" />



	
	
	
	
	
	
	
	<param name="speed_factor" value="1.43" />
	
	
										
	<param name="speed_limit_add_on" value="-0.3125 -0.1969 -0.1281 -0.0732 -0.0238 0.0238 0.0732 0.1281 0.1969 0.3125" />

	
	

	
		
	
	
											
	<param name="target_gap_acc_parm" value="0.5 0.45881 0.5926 0.03 0.33562 0.29446 -0.6455 -0.36248 0.093984 0.187 0.9562 0.064348 0.32203" />
	
	 
	
	
	<param name="max_acc_car1" value="5.898 5.8141 4.9786 4.2734 4.3185" />
	
	<param name="normal_deceleration_car1" value="-2.25 -2.025 -1.8741 -1.575 -1.65" />
	
	<param name="max_deceleration_car1" value="-8.2967 -7.8705 -7.4489 -8.0183 -6.6527" />

	
												
	<param name="max_acceleration_scale" value="0.75 0.80 0.85 0.90 0.95 1.00 1.05 1.10 1.15 1.20" />
	<param name="normal_deceleration_scale" value="0.75 0.80 0.85 0.90 0.95 1.00 1.05 1.10 1.15 1.20" />
	<param name="max_deceleration_scale" value="0.75 0.80 0.85 0.90 0.95 1.00 1.05 1.10 1.15 1.20" />
	
	
		
	<param name="speed_scaler" value="5 10 5" />
	
	<param name="acceleration_grade_factor" value="1" />
	
	<param name="tmp_all_grades" value="0" />

	


	
	
  <param name="hbuffer_lower" value="0.91593" />
  
	
	
											
	
	
	
	
	
	<param name="hbuffer_Upper" value="1.8305 2.0883 2.2429 2.3461 2.475 2.5781 2.6812 2.8101 2.9648 3.2226" />


	<param name="yellow_stop_headway" value="0.95385" />	
	<param name="min_speed_yellow" value="2.0117" />	
	<param name="driver_signal_perception_distance" value="135" /> 


														
	
	
	

	
	

	<param name="dec_update_step_size" value="0.41061 0.10 0.25 1.05 0.0" />
	<param name="acc_update_step_size" value="0.55 0.10 0.30 1.55 0.0" />
	<param name="uniform_speed_update_step_size" value="0.55 0.10 0.30 1.55 0.0" />
	<param name="stopped_vehicle_update_step_size" value="0.41061 0.10 0.25 1.05 0.0" />



	<param name="visibility_distance" value="10" />



                                   
	<param name="MLC_PARAMETERS" value="1000 703.573 2" />
	
	


	
	
	
	
	
	
	<param name="lane_utility_model" value="2 0.31144 -0.75 0 0.03688 -0.59451 0.0083512 -0.31479 -0.0052966 -3.0171 7.3713 20.0648 -1.6128 -3.7626 -1.656 -0.8005 -0.68186 -0.17924" />



									
	<param name="LC_GAP_MODELS_0" value="1.00, 0.0, 0.000, 0.508, 0.000, 0.000, -0.420, 0.000, 0.488" />
	<param name="LC_GAP_MODELS_1" value="1.00, 0.0, 0.000, 2.020, 0.000, 0.000, 0.153, 0.188, 0.526" />
	<param name="LC_GAP_MODELS_2" value="1.00, 0.0, 0.000, 0.384, 0.000, 0.000, 0.000, 0.000, 0.859" />
	<param name="LC_GAP_MODELS_3" value="1.00, 0.0, 0.000, 0.587, 0.000, 0.000, 0.048, 0.356, 1.073" />
	<param name="LC_GAP_MODELS_4" value="0.60, 0.0, 0.000, 0.384, 0.000, 0.000, 0.000, 0.000, 0.859" />
	<param name="LC_GAP_MODELS_5" value="0.60, 0.0, 0.000, 0.587, 0.000, 0.000, 0.048, 0.356, 1.073" />
	<param name="LC_GAP_MODELS_6" value="0.20, 0.0, 0.000, 0.384, 0.000, 0.000, 0.000, 0.000, 0.859" />
	<param name="LC_GAP_MODELS_7" value="0.20, 0.0, 0.000, 0.587, 0.000, 0.000, 0.048, 0.356, 1.073" />

	<param name="critical_gaps_param" value="0.63771 -0.18553 -2.647 0.95919 0.76875 0 0.61648 0.90412 0.84523" />

	
	<param name="Target_Gap_Model" value="-0.86649 1.0043 0.7344 -1.3398 -2.6323 -1.4958" />


									
	<param name="GAP_PARAM_0" value="-1.23, -0.482, 0.224, -0.0179, 2.10, 0.239" />   #back
	<param name="GAP_PARAM_1" value="0.00, 0.00, 0.224, -0.0179, 2.10, 0.000" />   #adj
	<param name="GAP_PARAM_2" value="-0.772, -0.482, 0.224, -0.0179, 2.10, 0.675" />   #fwd



	<param name="nosing_param" value="0.92638 0.55 0.54 0.098267 0.55 0.9 31.5516 94.528 604.5192 36" />
	



	<param name="kazi_nosing_param" value="-3.159 0.313 -0.027 2.050 0.028 0.6" />

	
	<param name="CF_CRITICAL_TIMER_RATIO" value="0.45" />

	
	<param name="LC_Yielding_Model" value="0.80 1.00" />
	
	
	
	<param name="MLC_Yielding_Probabilities" value="0.13 0.71 0.13 0.03" />
	

	
	
	<param name="intersection_attentiveness_factor_min" value="0.33" />
	<param name="intersection_attentivneess_factor_max" value="0.66" />
	
	
	<param name="minimum_gap" value="1.375" />
	
	
										
	<param name="critical_gap_addon" value="0.94528 0.45 0.5" />
	
	
	<param name="impatience_factor" value="0.18741" />
	
	
	
	
	<param name="tailgate_separation_time" value="1" />
	
	
	<param name="conflict_separation_time" value="2.46" />	
	
	
	
	<param name="min_speed" value="0.1" />  
	
	
	<param name="LC_Discretionary_Lane_Change_Model_MinTimeInLaneSameDir" value="6.8565" /> 
	<param name="LC_Discretionary_Lane_Change_Model_MinTimeInLaneDiffDir" value="13.5" /> 

	
	<param name="check_stop_point_distance" value="200" /> 

	
	<param name="density" value="0.0" /> 
	
</parameters>